Metadata-Version: 1.1
Name: conbasiccalculator
Version: 0.0.1
Summary: A calculator module that does math
Home-page: UNKNOWN
Author: Joshua Lowe
Author-email: codewaltz52@gmail.com
License: MIT
Keywords: calculator
Platform: UNKNOWN
Classifier: Development Status :: 5 - Production/Stable
Classifier: Intended Audience :: Education
Classifier: Operating System :: Microsoft :: Windows :: Windows 10
Classifier: License :: OSI Approved :: MIT License
Classifier: Programming Language :: Python :: 3
